llamanet/__init__.py
llamanet-0.12.dist-info/METADATA
llamanet-0.12.dist-info/WHEEL
llamanet-0.12.dist-info/top_level.txt
llamanet-0.12.dist-info/RECORD
