Metadata-Version: 2.1
Name: llamanet
Version: 0.12
Requires-Dist: requests
